oceanproc-1.1.7.dist-info/METADATA
oceanproc-1.1.7.dist-info/WHEEL
oceanproc-1.1.7.dist-info/entry_points.txt
oceanproc/__init__.py
oceanproc/bids_wrapper.py
oceanproc/events_long.py
oceanproc/firstlevel/Ocean-Proc.code-workspace
oceanproc/firstlevel/__init__.py
oceanproc/firstlevel/run_glm.py
oceanproc/firstlevel/tests/__init__.py
oceanproc/firstlevel/tests/test_run_glm.py
oceanproc/group_series.py
oceanproc/grouplevel/__init__.py
oceanproc/grouplevel/computations.py
oceanproc/grouplevel/design_mat_utils.py
oceanproc/grouplevel/dscalar_utils.py
oceanproc/grouplevel/utils.py
oceanproc/ocean_proc.py
oceanproc/oceanparse.py
oceanproc/preprocessing_wrapper.py
oceanproc/segmentation_wrapper.py
oceanproc/utils.py
oceanproc-1.1.7.dist-info/RECORD
