Metadata-Version: 2.1
Name: oceanproc
Version: 1.1.7
Summary: MRI preprocessing for WUSTL Ocean labs
Author-Email: Ramone Agard <rhagard@wustl.edu>, Joey Scanga <joeyscanga92@gmail.com>
Requires-Python: <3.13,>=3.10
Requires-Dist: flask<4.0.0,>=3.0.3
Requires-Dist: asttokens<3.0.0,>=2.4.1
Requires-Dist: numpy>=1.26.0
Requires-Dist: pandas<3.0.0,>=2.2.2
Requires-Dist: nilearn<1.0.0,>=0.10.4
Requires-Dist: scipy>=1.13.0
Requires-Dist: matplotlib<4.0.0,>=3.9.1
Requires-Dist: beautifulsoup4>=4.12.0
Requires-Dist: pybids>=0.16.3
